LICENSE
MANIFEST.in
README.rst
setup.py
dictpatterns/__init__.py
dictpatterns/tests.py
dictpatterns/templatetags/__init__.py
dictpatterns/templatetags/dict_url_tools.py
dictpatterns/urls/__init__.py
dictpatterns/urls/dictpatterns.py
django_dictpatterns.egg-info/PKG-INFO
django_dictpatterns.egg-info/SOURCES.txt
django_dictpatterns.egg-info/dependency_links.txt
django_dictpatterns.egg-info/top_level.txt