Metadata-Version: 1.1
Name: django-dictpatterns
Version: 0.1
Summary: This makes your application be able to write simple urlpatterns with dictionary for Django
Home-page: https://github.com/luyikei/django-dictpatterns
Author: luyikei
Author-email: luyikei.qmltu@gmail.com
License: UNKNOWN
Download-URL: https://github.com/luyikei/django-dictpatterns/archive/0.1.zip
Platform: UNKNOWN
Classifier: Development Status :: 3 - Alpha
Classifier: Environment :: Web Environment
Classifier: Framework :: Django
Classifier: Intended Audience :: Developers
Classifier: License :: OSI Approved :: MIT License
Classifier: Operating System :: OS Independent
Classifier: Programming Language :: Python
Classifier: Topic :: Software Development :: Libraries :: Python Modules
Classifier: Topic :: Utilities
